[
  {
    "Surname": "Jordi Alba",
    "Shoot": 74,
    "Pass": 86,
    "Tackle": 78,
    "Interception": 70,
    "Stamina": 75
  },
  {
    "Surname": "Ronald Araújo",
    "Shoot": 49,
    "Pass": 78,
    "Tackle": 82,
    "Interception": 84,
    "Stamina": 85
  },
  {
    "Surname": "Gerard Piqué",
    "Shoot": 67,
    "Pass": 75,
    "Tackle": 78,
    "Interception": 72,
    "Stamina": 69
  },
  {
    "Surname": "Sergiño Dest",
    "Shoot": 59,
    "Pass": 70,
    "Tackle": 74,
    "Interception": 73,
    "Stamina": 86
  },
  {
    "Surname": "Eric García",
    "Shoot": 45,
    "Pass": 74,
    "Tackle": 78,
    "Interception": 72,
    "Stamina": 80
  },
  {
    "Surname": "Éder Militão",
    "Shoot": 52,
    "Pass": 80,
    "Tackle": 81,
    "Interception": 83,
    "Stamina": 86
  },
  {
    "Surname": "David Alaba",
    "Shoot": 67,
    "Pass": 72,
    "Tackle": 84,
    "Interception": 82,
    "Stamina": 88
  },
  {
    "Surname": "Nacho Fernández",
    "Shoot": 35,
    "Pass": 68,
    "Tackle": 74,
    "Interception": 75,
    "Stamina": 78
  },
  {
    "Surname": "Ferland Mendy",
    "Shoot": 57,
    "Pass": 80,
    "Tackle": 79,
    "Interception": 80,
    "Stamina": 90
  },
  {
    "Surname": "Daniel Carvajal",
    "Shoot": 47,
    "Pass": 72,
    "Tackle": 76,
    "Interception": 70,
    "Stamina": 73
  },
  {
    "Surname": "Rüdiger",
    "Shoot": 33,
    "Pass": 75,
    "Tackle": 86,
    "Interception": 82,
    "Stamina": 90
  },
  {
    "Surname": "Alonso",
    "Shoot": 65,
    "Pass": 67,
    "Tackle": 63,
    "Interception": 55,
    "Stamina": 65
  },
  {
    "Surname": "Thiago Silva",
    "Shoot": 46,
    "Pass": 79,
    "Tackle": 81,
    "Interception": 78,
    "Stamina": 67
  },
  {
    "Surname": " Azpilicueta",
    "Shoot": 65,
    "Pass": 72,
    "Tackle": 76,
    "Interception": 67,
    "Stamina": 62
  },
  {
    "Surname": "James",
    "Shoot": 35,
    "Pass": 80,
    "Tackle": 81,
    "Interception": 76,
    "Stamina": 87
  },
  {
    "Surname": "van Dijk",
    "Shoot": 37,
    "Pass": 82,
    "Tackle": 95,
    "Interception": 93,
    "Stamina": 93
  },
  {
    "Surname": "Konaté",
    "Shoot": 21,
    "Pass": 70,
    "Tackle": 65,
    "Interception": 61,
    "Stamina": 64
  },
  {
    "Surname": "Matip",
    "Shoot": 16,
    "Pass": 78,
    "Tackle": 81,
    "Interception": 86,
    "Stamina": 69
  },
  {
    "Surname": "Trent Alexander-Arnold",
    "Shoot": 68,
    "Pass": 84,
    "Tackle": 73,
    "Interception": 68,
    "Stamina": 91
  },
  {
    "Surname": "Robertson",
    "Shoot": 57,
    "Pass": 81,
    "Tackle": 82,
    "Interception": 80,
    "Stamina": 96
  }
]